mlchat/__init__.py
mlchat/extension.py
mlchat/__pycache__/__init__.cpython-312.pyc
mlchat/__pycache__/extension.cpython-312.pyc
mlchat-1.0.8.dist-info/METADATA
mlchat-1.0.8.dist-info/WHEEL
mlchat-1.0.8.dist-info/top_level.txt
mlchat-1.0.8.dist-info/RECORD
