Metadata-Version: 2.4
Name: mlchat
Version: 1.0.8
Summary: opean+mcp调用工具
Home-page: https://www.python.org
Author: mengling
Author-email: 1321443305@qq.com
Requires-Python: >=3.8
Requires-Dist: loguru
Requires-Dist: openai
Requires-Dist: mcp>=1.25.0
Requires-Dist: pydantic
Requires-Dist: json-repair
Dynamic: author
Dynamic: author-email
Dynamic: home-page
Dynamic: requires-dist
Dynamic: requires-python
Dynamic: summary
